{"parameters":{"historySize":1300,"SMA_long":500,"SMA_short":20,"BULL_RSI":12,"BULL_RSI_high":49,"BULL_RSI_low":36,"BEAR_RSI":19,"BEAR_RSI_high":54,"BEAR_RSI_low":50,"BULL_MOD_high":2,"BULL_MOD_low":-6,"BEAR_MOD_high":9,"BEAR_MOD_low":-5,"ADX":4,"ADX_high":75,"ADX_low":44,"SMA_Timeframe":80,"BULL_RSI_Timeframe":70,"BEAR_RSI_Timeframe":7,"ADX_Timeframe":50,"candleSize":1},"score":0,"profit":0,"sharpe":0,"epochNumber":180,"otherMetrics":{"balance":5645268.5522553185,"profit":5645168.5522553185,"sharpe":-2.902142371909609,"market":31.85714285714286,"relativeProfit":5645168.5522553185,"yearlyProfit":"11969602.55723155","relativeYearlyProfit":"11969602.55723155","startPrice":0.000007,"endPrice":0.00000923,"trades":11033}}